webexception/__init__.py
webexception/webexception.py
webexception-1.0.5.dist-info/METADATA
webexception-1.0.5.dist-info/WHEEL
webexception-1.0.5.dist-info/RECORD
