Metadata-Version: 2.1
Name: webexception
Version: 1.0.5
Summary: 
Author: Marco Bartel
Author-email: bsimpson888@gmail.com
Requires-Python: >=3.9,<4.0
Classifier: Programming Language :: Python :: 3
Classifier: Programming Language :: Python :: 3.9
Classifier: Programming Language :: Python :: 3.10
Classifier: Programming Language :: Python :: 3.11
